<annotation verified="yes">
	<folder>20210511_1120</folder>
	<filename>frame0080.jpg</filename>
	<path>/home/vagrant/workspace-pycharm/01_video-to-images/image/20210511_1120/frame0080.jpg</path>
	<source>
		<database>Unknown</database>
	</source>
	<size>
		<width>1080</width>
		<height>1920</height>
		<depth>3</depth>
	</size>
	<segmented>0</segmented>
	<object>
		<name>bee-no-pollen</name>
		<pose>Unspecified</pose>
		<truncated>0</truncated>
		<difficult>0</difficult>
		<bndbox>
			<xmin>284</xmin>
			<ymin>1031</ymin>
			<xmax>451</xmax>
			<ymax>1185</ymax>
		</bndbox>
	</object>
	<object>
		<name>bee-no-pollen</name>
		<pose>Unspecified</pose>
		<truncated>0</truncated>
		<difficult>0</difficult>
		<bndbox>
			<xmin>201</xmin>
			<ymin>961</ymin>
			<xmax>388</xmax>
			<ymax>1116</ymax>
		</bndbox>
	</object>
	<object>
		<name>bee-shadow</name>
		<pose>Unspecified</pose>
		<truncated>0</truncated>
		<difficult>0</difficult>
		<bndbox>
			<xmin>208</xmin>
			<ymin>1036</ymin>
			<xmax>368</xmax>
			<ymax>1128</ymax>
		</bndbox>
	</object>
	<object>
		<name>bee-with-pollen</name>
		<pose>Unspecified</pose>
		<truncated>0</truncated>
		<difficult>0</difficult>
		<bndbox>
			<xmin>279</xmin>
			<ymin>674</ymin>
			<xmax>441</xmax>
			<ymax>812</ymax>
		</bndbox>
	</object>
	<object>
		<name>bee-shadow</name>
		<pose>Unspecified</pose>
		<truncated>0</truncated>
		<difficult>0</difficult>
		<bndbox>
			<xmin>642</xmin>
			<ymin>694</ymin>
			<xmax>790</xmax>
			<ymax>829</ymax>
		</bndbox>
	</object>
	<object>
		<name>bee-shadow</name>
		<pose>Unspecified</pose>
		<truncated>0</truncated>
		<difficult>0</difficult>
		<bndbox>
			<xmin>520</xmin>
			<ymin>1108</ymin>
			<xmax>695</xmax>
			<ymax>1222</ymax>
		</bndbox>
	</object>
	<object>
		<name>bee-no-pollen</name>
		<pose>Unspecified</pose>
		<truncated>0</truncated>
		<difficult>0</difficult>
		<bndbox>
			<xmin>292</xmin>
			<ymin>598</ymin>
			<xmax>451</xmax>
			<ymax>725</ymax>
		</bndbox>
	</object>
	<object>
		<name>bee-shadow</name>
		<pose>Unspecified</pose>
		<truncated>0</truncated>
		<difficult>0</difficult>
		<bndbox>
			<xmin>210</xmin>
			<ymin>853</ymin>
			<xmax>373</xmax>
			<ymax>943</ymax>
		</bndbox>
	</object>
	<object>
		<name>bee-shadow</name>
		<pose>Unspecified</pose>
		<truncated>0</truncated>
		<difficult>0</difficult>
		<bndbox>
			<xmin>818</xmin>
			<ymin>1234</ymin>
			<xmax>942</xmax>
			<ymax>1323</ymax>
		</bndbox>
	</object>
	<object>
		<name>bee-no-pollen</name>
		<pose>Unspecified</pose>
		<truncated>0</truncated>
		<difficult>0</difficult>
		<bndbox>
			<xmin>300</xmin>
			<ymin>640</ymin>
			<xmax>431</xmax>
			<ymax>742</ymax>
		</bndbox>
	</object>
	<object>
		<name>bee-shadow</name>
		<pose>Unspecified</pose>
		<truncated>0</truncated>
		<difficult>0</difficult>
		<bndbox>
			<xmin>254</xmin>
			<ymin>1115</ymin>
			<xmax>434</xmax>
			<ymax>1169</ymax>
		</bndbox>
	</object>
</annotation>
